README.rst
ponytor.py
setup.py
ponytor.egg-info/PKG-INFO
ponytor.egg-info/SOURCES.txt
ponytor.egg-info/dependency_links.txt
ponytor.egg-info/entry_points.txt
ponytor.egg-info/requires.txt
ponytor.egg-info/top_level.txt