Metadata-Version: 1.1
Name: ponytor
Version: 0.1.2
Summary: A small command line utility and python lib to run automated things when files change
Home-page: http://github.com/fisadev/ponytor
Author: Juan Pedro Fisanotti
Author-email: fisadev@gmail.com
License: LICENSE.txt
Platform: UNKNOWN
Classifier: Intended Audience :: Developers
Classifier: License :: OSI Approved :: MIT License
Classifier: Natural Language :: English
Classifier: Operating System :: OS Independent
Classifier: Programming Language :: Python
